pymimir_rl/__init__.py
pymimir_rl/algorithms.py
pymimir_rl/evaluations.py
pymimir_rl/goal_condition_sampling.py
pymimir_rl/heuristics.py
pymimir_rl/initial_state_sampling.py
pymimir_rl/loss_functions.py
pymimir_rl/loss_functions_dqn.py
pymimir_rl/loss_functions_iqn.py
pymimir_rl/loss_functions_sac.py
pymimir_rl/loss_functions_td3.py
pymimir_rl/models.py
pymimir_rl/problem_sampling.py
pymimir_rl/replay_buffers.py
pymimir_rl/reward_functions.py
pymimir_rl/subtrajectory_sampling.py
pymimir_rl/trajectories.py
pymimir_rl/trajectory_refinements.py
pymimir_rl/trajectory_sampling.py
pymimir_rl/trajectory_sampling_beam.py
pymimir_rl/trajectory_sampling_multiple.py
pymimir_rl/trajectory_sampling_policy.py
pymimir_rl-0.2.5.dist-info/licenses/LICENSE
pymimir_rl-0.2.5.dist-info/METADATA
pymimir_rl-0.2.5.dist-info/WHEEL
pymimir_rl-0.2.5.dist-info/top_level.txt
pymimir_rl-0.2.5.dist-info/RECORD
